Metadata-Version: 2.1
Name: msaCRUD
Version: 0.0.1
Summary: msaCRUD - SQLModel/SQLAlchemy/FastAPI - DB Object CRUD/API Automation
Home-page: https://github.com/swelcker/msaCRUD
Download-URL: http://pypi.python.org/pypi/msaCRUD
Author: Stefan Welcker
Author-email: stefan@u2d.ai
License: MIT
Project-URL: Documentation, http://msaCRUD.u2d.ai/
Project-URL: Source, https://github.com/swelcker/msaCRUD
Project-URL: Tracker, https://github.com/swelcker/msaCRUD/issues
Classifier: Development Status :: 4 - Beta
Classifier: Framework :: FastAPI
Classifier: Intended Audience :: Developers
Classifier: License :: OSI Approved :: MIT License
Classifier: Operating System :: MacOS :: MacOS X
Classifier: Operating System :: Microsoft :: Windows
Classifier: Operating System :: POSIX :: Linux
Classifier: Programming Language :: Python :: 3
Classifier: Programming Language :: Python :: 3.7
Classifier: Programming Language :: Python :: 3.8
Classifier: Programming Language :: Python :: 3.9
Classifier: Programming Language :: Python :: 3.10
Classifier: Topic :: Database
Classifier: Topic :: Database :: Front-Ends
Classifier: Topic :: Documentation
Classifier: Topic :: Internet :: WWW/HTTP :: WSGI :: Server
Classifier: Topic :: Software Development :: Libraries
Classifier: Topic :: Software Development :: Libraries :: Python Modules
License-File: LICENCE
